{
  "asks": [
    {
      "price": "0.999",
      "size": "1129.38"
    },
    {
      "price": "0.998",
      "size": "605.69"
    },
    {
      "price": "0.997",
      "size": "25007.56"
    },
    {
      "price": "0.996",
      "size": "530"
    },
    {
      "price": "0.995",
      "size": "11.33"
    },
    {
      "price": "0.99",
      "size": "2050"
    },
    {
      "price": "0.989",
      "size": "12.7"
    },
    {
      "price": "0.98",
      "size": "2100"
    },
    {
      "price": "0.978",
      "size": "2000"
    },
    {
      "price": "0.97",
      "size": "1025"
    },
    {
      "price": "0.969",
      "size": "5.11"
    },
    {
      "price": "0.96",
      "size": "1100"
    },
    {
      "price": "0.95",
      "size": "1020"
    },
    {
      "price": "0.94",
      "size": "1000"
    },
    {
      "price": "0.93",
      "size": "1000"
    },
    {
      "price": "0.92",
      "size": "1000"
    },
    {
      "price": "0.919",
      "size": "5.43"
    },
    {
      "price": "0.91",
      "size": "1000"
    },
    {
      "price": "0.9",
      "size": "4300"
    },
    {
      "price": "0.89",
      "size": "600"
    },
    {
      "price": "0.822",
      "size": "140"
    },
    {
      "price": "0.82",
      "size": "600"
    },
    {
      "price": "0.818",
      "size": "450"
    },
    {
      "price": "0.816",
      "size": "300"
    },
    {
      "price": "0.815",
      "size": "630"
    },
    {
      "price": "0.814",
      "size": "11448.6"
    },
    {
      "price": "0.804",
      "size": "7.93"
    },
    {
      "price": "0.8",
      "size": "5"
    },
    {
      "price": "0.75",
      "size": "5"
    },
    {
      "price": "0.7",
      "size": "1110"
    },
    {
      "price": "0.699",
      "size": "444"
    },
    {
      "price": "0.65",
      "size": "5"
    },
    {
      "price": "0.6",
      "size": "830"
    },
    {
      "price": "0.596",
      "size": "185"
    },
    {
      "price": "0.55",
      "size": "5"
    },
    {
      "price": "0.549",
      "size": "267.09"
    },
    {
      "price": "0.5",
      "size": "5"
    },
    {
      "price": "0.499",
      "size": "5"
    },
    {
      "price": "0.45",
      "size": "5"
    },
    {
      "price": "0.4",
      "size": "5"
    },
    {
      "price": "0.38",
      "size": "7"
    },
    {
      "price": "0.379",
      "size": "1575"
    },
    {
      "price": "0.378",
      "size": "630"
    },
    {
      "price": "0.376",
      "size": "502.4"
    },
    {
      "price": "0.375",
      "size": "1367"
    },
    {
      "price": "0.37",
      "size": "5"
    },
    {
      "price": "0.36",
      "size": "7"
    },
    {
      "price": "0.35",
      "size": "10"
    },
    {
      "price": "0.349",
      "size": "100"
    },
    {
      "price": "0.326",
      "size": "30"
    },
    {
      "price": "0.324",
      "size": "25"
    },
    {
      "price": "0.3",
      "size": "5"
    },
    {
      "price": "0.299",
      "size": "50"
    },
    {
      "price": "0.25",
      "size": "55"
    },
    {
      "price": "0.249",
      "size": "45"
    },
    {
      "price": "0.247",
      "size": "30"
    },
    {
      "price": "0.242",
      "size": "30"
    },
    {
      "price": "0.22",
      "size": "5"
    },
    {
      "price": "0.219",
      "size": "30"
    },
    {
      "price": "0.2",
      "size": "35"
    },
    {
      "price": "0.18",
      "size": "48"
    },
    {
      "price": "0.15",
      "size": "5"
    },
    {
      "price": "0.1",
      "size": "5"
    },
    {
      "price": "0.05",
      "size": "32"
    },
    {
      "price": "0.026",
      "size": "30"
    },
    {
      "price": "0.025",
      "size": "452"
    },
    {
      "price": "0.024",
      "size": "171"
    },
    {
      "price": "0.021",
      "size": "32"
    },
    {
      "price": "0.02",
      "size": "143.89"
    },
    {
      "price": "0.019",
      "size": "7.81"
    },
    {
      "price": "0.016",
      "size": "31"
    },
    {
      "price": "0.015",
      "size": "92.87"
    }
  ],
  "asset_id": "83418331973269326342842796628927411903404188505902736961426142875458158167920",
  "bids": [
    {
      "price": "0.001",
      "size": "2149.31"
    },
    {
      "price": "0.002",
      "size": "83.93"
    },
    {
      "price": "0.003",
      "size": "230"
    },
    {
      "price": "0.005",
      "size": "185"
    },
    {
      "price": "0.007",
      "size": "41"
    },
    {
      "price": "0.008",
      "size": "375"
    },
    {
      "price": "0.01",
      "size": "143.33"
    }
  ],
  "hash": "8405dd093640427a2f95c60a31e1974fc576627c",
  "last_trade_price": "0.010",
  "market": "0x52968e878027b25743b71d8cccda0af8ae17ee093c6a1017b65c8d7aaad72145",
  "min_order_size": "5",
  "neg_risk": true,
  "tick_size": "0.001",
  "timestamp": "1783066511282"
}